sql2pandas/__init__.py
sql2pandas/baseops.py
sql2pandas/context.py
sql2pandas/db.py
sql2pandas/exprs.py
sql2pandas/exprutil.py
sql2pandas/parse_expr.py
sql2pandas/parse_sql.py
sql2pandas/parseops.py
sql2pandas/schema.py
sql2pandas/stats.py
sql2pandas/tables.py
sql2pandas/tuples.py
sql2pandas/udfs.py
sql2pandas/util.py
sql2pandas/compile/__init__.py
sql2pandas/compile/agg.py
sql2pandas/compile/compiledquery.py
sql2pandas/compile/compiler.py
sql2pandas/compile/hashjoin.py
sql2pandas/compile/limit.py
sql2pandas/compile/orderby.py
sql2pandas/compile/pipeline.py
sql2pandas/compile/project.py
sql2pandas/compile/root.py
sql2pandas/compile/scan.py
sql2pandas/compile/thetajoin.py
sql2pandas/compile/translator.py
sql2pandas/compile/where.py
sql2pandas/compile/pandas/__init__.py
sql2pandas/compile/pandas/agg.py
sql2pandas/compile/pandas/compiledquery.py
sql2pandas/compile/pandas/hashjoin.py
sql2pandas/compile/pandas/limit.py
sql2pandas/compile/pandas/orderby.py
sql2pandas/compile/pandas/pipeline.py
sql2pandas/compile/pandas/project.py
sql2pandas/compile/pandas/root.py
sql2pandas/compile/pandas/scan.py
sql2pandas/compile/pandas/thetajoin.py
sql2pandas/compile/pandas/translator.py
sql2pandas/compile/pandas/where.py
sql2pandas/ops/__init__.py
sql2pandas/ops/agg.py
sql2pandas/ops/distinct.py
sql2pandas/ops/hashjoin.py
sql2pandas/ops/join.py
sql2pandas/ops/limit.py
sql2pandas/ops/orderby.py
sql2pandas/ops/project.py
sql2pandas/ops/root.py
sql2pandas/ops/scan.py
sql2pandas/ops/where.py
sql2pandas/optimizer/__init__.py
sql2pandas/optimizer/estimation.py
sql2pandas/optimizer/joinopt.py
sql2pandas/optimizer/optimizer.py
sql2pandas/optimizer/selinger.py
sql2pandas-0.0.4.dist-info/LICENSE
sql2pandas-0.0.4.dist-info/METADATA
sql2pandas-0.0.4.dist-info/WHEEL
sql2pandas-0.0.4.dist-info/top_level.txt
sql2pandas-0.0.4.dist-info/RECORD
